pixelpin_auth_core/__init__.py
pixelpin_auth_core/actions.py
pixelpin_auth_core/exceptions.py
pixelpin_auth_core/storage.py
pixelpin_auth_core/store.py
pixelpin_auth_core/strategy.py
pixelpin_auth_core/utils.py
pixelpin_auth_core/backends/__init__.py
pixelpin_auth_core/backends/base.py
pixelpin_auth_core/backends/oauth.py
pixelpin_auth_core/backends/open_id_connect.py
pixelpin_auth_core/backends/pixelpin.py
pixelpin_auth_core/backends/utils.py
pixelpin_auth_core/pipeline/__init__.py
pixelpin_auth_core/pipeline/debug.py
pixelpin_auth_core/pipeline/disconnect.py
pixelpin_auth_core/pipeline/mail.py
pixelpin_auth_core/pipeline/partial.py
pixelpin_auth_core/pipeline/pixelpin_auth.py
pixelpin_auth_core/pipeline/user.py
pixelpin_auth_core/pipeline/utils.py
pixelpin_auth_core/tests/__init__.py
pixelpin_auth_core/tests/models.py
pixelpin_auth_core/tests/pipeline.py
pixelpin_auth_core/tests/requirements-base.txt
pixelpin_auth_core/tests/requirements-pypy.txt
pixelpin_auth_core/tests/requirements-python2.txt
pixelpin_auth_core/tests/requirements-python3.txt
pixelpin_auth_core/tests/requirements.txt
pixelpin_auth_core/tests/strategy.py
pixelpin_auth_core/tests/test_exceptions.py
pixelpin_auth_core/tests/test_pipeline.py
pixelpin_auth_core/tests/test_storage.py
pixelpin_auth_core/tests/test_utils.py
pixelpin_auth_core/tests/testkey.pem
pixelpin_auth_core/tests/actions/__init__.py
pixelpin_auth_core/tests/actions/actions.py
pixelpin_auth_core/tests/actions/test_associate.py
pixelpin_auth_core/tests/actions/test_disconnect.py
pixelpin_auth_core/tests/actions/test_login.py
pixelpin_auth_core/tests/backends/__init__.py
pixelpin_auth_core/tests/backends/data/saml_response.txt
pixelpin_auth_core-1.0.0.dist-info/DESCRIPTION.rst
pixelpin_auth_core-1.0.0.dist-info/METADATA
pixelpin_auth_core-1.0.0.dist-info/RECORD
pixelpin_auth_core-1.0.0.dist-info/WHEEL
pixelpin_auth_core-1.0.0.dist-info/metadata.json
pixelpin_auth_core-1.0.0.dist-info/top_level.txt
