Metadata-Version: 2.0
Name: pixelpin-auth-core
Version: 1.0.0
Summary: Python PixelPin authentication made simple.
Home-page: https://github.com/PixelPinPlugins/pixelpin-auth-core
Author: ['Matias Aguirre', 'Callum Brankin']
Author-email: callum@pixelpin.co.uk
License: BSD
Keywords: openid,oauth,saml,social auth,pixelpin auth,openid connect
Platform: UNKNOWN
Classifier: Development Status :: 4 - Beta
Classifier: Topic :: Internet
Classifier: License :: OSI Approved :: BSD License
Classifier: Intended Audience :: Developers
Classifier: Environment :: Web Environment
Classifier: Programming Language :: Python
Classifier: Programming Language :: Python :: 2.7
Classifier: Programming Language :: Python :: 3
Requires-Dist: PyJWT (>=1.4.0)
Requires-Dist: oauthlib (>=1.0.3)
Requires-Dist: requests (>=2.9.1)
Requires-Dist: requests-oauthlib (>=0.6.1)
Requires-Dist: six (>=1.10.0)
Provides-Extra: all
Requires-Dist: pyjwkest (>=1.0.1); extra == 'all'
Requires-Dist: python-saml (>=2.2.0); extra == 'all'
Provides-Extra: openidconnect
Requires-Dist: pyjwkest (>=1.0.1); extra == 'openidconnect'
Provides-Extra: saml
Requires-Dist: python-saml (>=2.2.0); extra == 'saml'
